{
  "node": {
    "distro": {
      "prefix": "http://localhost/node/distro/"
    },
    "latest": {
      "prefix": "http://localhost/node/latest/"
    },
    "index": {
      "prefix": "http://localhost/node/index/"
    }
  },
  "pnpm": {
    "distro": {
      "prefix": "http://localhost/pnpm/distro/"
    },
    "latest": {
      "prefix": "http://localhost/pnpm/latest/"
    },
    "index": {
      "prefix": "http://localhost/pnpm/index/"
    }
  },
  "yarn": {
    "distro": {
      "prefix": "http://localhost/yarn/distro/"
    },
    "latest": {
      "prefix": "http://localhost/yarn/latest/"
    },
    "index": {
      "prefix": "http://localhost/yarn/index/"
    }
  }
}
